dissect/eventlog/__init__.py
dissect/eventlog/bxml.py
dissect/eventlog/evt.py
dissect/eventlog/evtx.py
dissect/eventlog/exceptions.py
dissect/eventlog/utils.py
dissect/eventlog/wevt.py
dissect/eventlog/wevt_object.py
dissect/eventlog/wevtutil.py
dissect.eventlog-3.9.dist-info/COPYRIGHT
dissect.eventlog-3.9.dist-info/LICENSE
dissect.eventlog-3.9.dist-info/METADATA
dissect.eventlog-3.9.dist-info/WHEEL
dissect.eventlog-3.9.dist-info/top_level.txt
dissect.eventlog-3.9.dist-info/RECORD
