Metadata-Version: 2.1
Name: dissect.eventlog
Version: 3.9
Summary: A Dissect module implementing parsers for the Windows EVT, EVTX and WEVT log file formats
Author-email: Dissect Team <dissect@fox-it.com>
License: Affero General Public License v3
Project-URL: homepage, https://dissect.tools
Project-URL: documentation, https://docs.dissect.tools/en/latest/projects/dissect.eventlog
Project-URL: repository, https://github.com/fox-it/dissect.eventlog
Classifier: Development Status :: 5 - Production/Stable
Classifier: Environment :: Console
Classifier: Intended Audience :: Developers
Classifier: Intended Audience :: Information Technology
Classifier: License :: OSI Approved
Classifier: Operating System :: OS Independent
Classifier: Programming Language :: Python :: 3
Classifier: Topic :: Internet :: Log Analysis
Classifier: Topic :: Scientific/Engineering :: Information Analysis
Classifier: Topic :: Security
Classifier: Topic :: Utilities
Requires-Python: ~=3.9
License-File: LICENSE
License-File: COPYRIGHT
Requires-Dist: dissect.cstruct <5,>=4
Requires-Dist: dissect.util <4,>=3
Provides-Extra: dev
Requires-Dist: dissect.cstruct <5.0.dev,>=4.0.dev ; extra == 'dev'
Requires-Dist: dissect.util <4.0.dev,>=3.0.dev ; extra == 'dev'
